mtpk_mariadb/__init__.py
mtpk_mariadb/async_adapter.py
mtpk_mariadb/async_adapter_OLD.py
mtpk_mariadb/core_sync.py
mtpk_mariadb/crud.py
mtpk_mariadb/excepciones.py
mtpk_mariadb/interface.py
mtpk_mariadb/utils.py
mtpk_mariadb-0.1.3.dist-info/licenses/LICENSE
mtpk_mariadb-0.1.3.dist-info/METADATA
mtpk_mariadb-0.1.3.dist-info/WHEEL
mtpk_mariadb-0.1.3.dist-info/top_level.txt
mtpk_mariadb-0.1.3.dist-info/RECORD
