Metadata-Version: 2.4
Name: mtpk_mariadb
Version: 0.1.3
Summary: Librería para sincronización estructural de bases de datos MariaDB con modelos Python
Author-email: José Jesús Andrés Zambrana <jjandres@multiplika.es>
License: MIT License
Project-URL: Homepage, https://github.com/jjandres/mtpk_mariadb
Project-URL: Repository, https://github.com/jjandres/mtpk_mariadb
Requires-Python: >=3.9
License-File: LICENSE
Requires-Dist: pymysql
Dynamic: license-file
